ipygoldenlayout/__init__.py
ipygoldenlayout/_version.py
ipygoldenlayout/widget.py
ipygoldenlayout/labextension/package.json
ipygoldenlayout/labextension/static/147.96f99aa60087d4df0324.js
ipygoldenlayout/labextension/static/261.6fd603642cc91e6ae419.js
ipygoldenlayout/labextension/static/546.84567dba6eca1b49cf67.js
ipygoldenlayout/labextension/static/755.71f97ba75516d689d256.js
ipygoldenlayout/labextension/static/755.71f97ba75516d689d256.js.LICENSE.txt
ipygoldenlayout/labextension/static/775.b7a51c292a56cfd5c738.js
ipygoldenlayout/labextension/static/775.b7a51c292a56cfd5c738.js.LICENSE.txt
ipygoldenlayout/labextension/static/874.9f7936838422b0b02d56.js
ipygoldenlayout/labextension/static/97.348f2b8423a5ef5996f3.js
ipygoldenlayout/labextension/static/97.348f2b8423a5ef5996f3.js.LICENSE.txt
ipygoldenlayout/labextension/static/994.1b004f15b9113621bf49.js
ipygoldenlayout/labextension/static/994.1b004f15b9113621bf49.js.LICENSE.txt
ipygoldenlayout/labextension/static/remoteEntry.a57d7679b63d9f644147.js
ipygoldenlayout/labextension/static/style.js
ipygoldenlayout/nbextension/extension.js
ipygoldenlayout/nbextension/index.js
ipygoldenlayout/nbextension/index.js.map
ipygoldenlayout-0.4.0.data/data/etc/jupyter/nbconfig/notebook.d/jupyter-golden-layout.json
ipygoldenlayout-0.4.0.data/data/share/jupyter/labextensions/jupyter-golden-layout/package.json
ipygoldenlayout-0.4.0.data/data/share/jupyter/labextensions/jupyter-golden-layout/static/147.96f99aa60087d4df0324.js
ipygoldenlayout-0.4.0.data/data/share/jupyter/labextensions/jupyter-golden-layout/static/261.6fd603642cc91e6ae419.js
ipygoldenlayout-0.4.0.data/data/share/jupyter/labextensions/jupyter-golden-layout/static/546.84567dba6eca1b49cf67.js
ipygoldenlayout-0.4.0.data/data/share/jupyter/labextensions/jupyter-golden-layout/static/755.71f97ba75516d689d256.js
ipygoldenlayout-0.4.0.data/data/share/jupyter/labextensions/jupyter-golden-layout/static/755.71f97ba75516d689d256.js.LICENSE.txt
ipygoldenlayout-0.4.0.dist-info/METADATA
ipygoldenlayout-0.4.0.dist-info/WHEEL
ipygoldenlayout-0.4.0.dist-info/top_level.txt
ipygoldenlayout-0.4.0.dist-info/RECORD
